fir.v
module firfilter #(
    parameter DATA_SIZE = 9,
    parameter N_TAPS = 3
)
(
    input clk,
    input signed [DATA_SIZE-1:0] data,
    input data_ready,

    output reg [DATA_SIZE-1:0] res = 0
);


reg signed [DATA_SIZE-1:0] buff[N_TAPS-1:0];
reg signed [7:0] i = 0;
reg signed [7:0] j = 0;
reg signed [DATA_SIZE-1:0] coef[N_TAPS-1:0];

initial
begin
    buff[0] = 0;
    buff[1] = 0;
    buff[2] = 0;
    for(j=0; j<N_TAPS; j=j+1)
    begin
        coef[j] <= (j+i);
    end
end

always @(posedge data_ready) 
begin
    buff[0] = buff[1];
    buff[1] = buff[2];
    buff[2] = data;
    res = 0;
    for (i=0; i<N_TAPS; i=i+1)
    begin
        res = res + coef[i]*buff[i];
    end    
end

endmodule

test.v
module tb;
    reg clk = 0;
    parameter DATA_SIZE = 9;
    parameter N_TAPS = 3;
    reg signed [DATA_SIZE - 1:0] data = 'h753;

    reg data_ready = 0;

    reg signed [7:0] i = 0;
    reg signed [DATA_SIZE-1:0] buff[11:0];

    initial
    begin
        buff[0] <= 16'h10;
        buff[1] <= 16'h15;
        buff[2] <= 16'h20;
        buff[3] <= 16'h25;
        buff[4] <= 16'h30; 
        buff[5] <= 16'h35;
        buff[6] <= 16'h40;
        buff[7] <= 16'h45;
        buff[8] <= 16'h50;
        buff[9] <= 16'h55;
        buff[10] <= 16'h60;
        buff[11] <= 16'h65;
    end

    initial 
    begin
        forever #20 clk = ~clk; 
    end

    initial
    begin
        for(i=0; i<12; i=i+1)
        begin
            data_ready = 0;
            #380;
            data_ready = 1;
            data <= buff[i];
            #20;
        end
    end

    initial
    begin
        #5000 $finish;
    end

    initial
    begin
        $dumpfile("dump.vcd");
        $dumpvars(0, tb);
    end

    firfilter #( .DATA_SIZE(DATA_SIZE),
    .N_TAPS(N_TAPS) )
    fir0 (
        .clk(clk),
        .data(data),
        .data_ready(data_ready)
    );

endmodule

dump.vcd
$date
	Mon Apr 17 15:13:31 2023
$end
$version
	Icarus Verilog
$end
$timescale
	1s
$end
$scope module tb $end
$var reg 1 ! clk $end
$var reg 9 " data [8:0] $end
$var reg 1 # data_ready $end
$var reg 8 $ i [7:0] $end
$scope module fir0 $end
$var wire 1 % clk $end
$var wire 9 & data [8:0] $end
$var wire 1 ' data_ready $end
$var reg 8 ( i [7:0] $end
$var reg 8 ) j [7:0] $end
$var reg 9 * res [8:0] $end
$upscope $end
$upscope $end
$enddefinitions $end
#0
$dumpvars
b0 *
b11 )
b0 (
0'
b101010011 &
0%
b0 $
0#
b101010011 "
0!
$end
#20
1!
1%
#40
0!
0%
#60
1!
1%
#80
0!
0%
#100
1!
1%
#120
0!
0%
#140
1!
1%
#160
0!
0%
#180
1!
1%
#200
0!
0%
#220
1!
1%
#240
0!
0%
#260
1!
1%
#280
0!
0%
#300
1!
1%
#320
0!
0%
#340
1!
1%
#360
0!
0%
#380
b10000 "
b10000 &
b10100110 *
b11 (
1!
1%
1#
1'
#400
0!
0%
0#
0'
b1 $
#420
1!
1%
#440
0!
0%
#460
1!
1%
#480
0!
0%
#500
1!
1%
#520
0!
0%
#540
1!
1%
#560
0!
0%
#580
1!
1%
#600
0!
0%
#620
1!
1%
#640
0!
0%
#660
1!
1%
#680
0!
0%
#700
1!
1%
#720
0!
0%
#740
1!
1%
#760
0!
0%
#780
b10101 "
b10101 &
b11 (
b101110011 *
1!
1%
1#
1'
#800
0!
0%
0#
0'
b10 $
#820
1!
1%
#840
0!
0%
#860
1!
1%
#880
0!
0%
#900
1!
1%
#920
0!
0%
#940
1!
1%
#960
0!
0%
#980
1!
1%
#1000
0!
0%
#1020
1!
1%
#1040
0!
0%
#1060
1!
1%
#1080
0!
0%
#1100
1!
1%
#1120
0!
0%
#1140
1!
1%
#1160
0!
0%
#1180
b100000 "
b100000 &
b11 (
b111010 *
1!
1%
1#
1'
#1200
0!
0%
0#
0'
b11 $
#1220
1!
1%
#1240
0!
0%
#1260
1!
1%
#1280
0!
0%
#1300
1!
1%
#1320
0!
0%
#1340
1!
1%
#1360
0!
0%
#1380
1!
1%
#1400
0!
0%
#1420
1!
1%
#1440
0!
0%
#1460
1!
1%
#1480
0!
0%
#1500
1!
1%
#1520
0!
0%
#1540
1!
1%
#1560
0!
0%
#1580
b100101 "
b100101 &
b11 (
b1010101 *
1!
1%
1#
1'
#1600
0!
0%
0#
0'
b100 $
#1620
1!
1%
#1640
0!
0%
#1660
1!
1%
#1680
0!
0%
#1700
1!
1%
#1720
0!
0%
#1740
1!
1%
#1760
0!
0%
#1780
1!
1%
#1800
0!
0%
#1820
1!
1%
#1840
0!
0%
#1860
1!
1%
#1880
0!
0%
#1900
1!
1%
#1920
0!
0%
#1940
1!
1%
#1960
0!
0%
#1980
b110000 "
b110000 &
b11 (
b1101010 *
1!
1%
1#
1'
#2000
0!
0%
0#
0'
b101 $
#2020
1!
1%
#2040
0!
0%
#2060
1!
1%
#2080
0!
0%
#2100
1!
1%
#2120
0!
0%
#2140
1!
1%
#2160
0!
0%
#2180
1!
1%
#2200
0!
0%
#2220
1!
1%
#2240
0!
0%
#2260
1!
1%
#2280
0!
0%
#2300
1!
1%
#2320
0!
0%
#2340
1!
1%
#2360
0!
0%
#2380
b110101 "
b110101 &
b11 (
b10000101 *
1!
1%
1#
1'
#2400
0!
0%
0#
0'
b110 $
#2420
1!
1%
#2440
0!
0%
#2460
1!
1%
#2480
0!
0%
#2500
1!
1%
#2520
0!
0%
#2540
1!
1%
#2560
0!
0%
#2580
1!
1%
#2600
0!
0%
#2620
1!
1%
#2640
0!
0%
#2660
1!
1%
#2680
0!
0%
#2700
1!
1%
#2720
0!
0%
#2740
1!
1%
#2760
0!
0%
#2780
b1000000 "
b1000000 &
b11 (
b10011010 *
1!
1%
1#
1'
#2800
0!
0%
0#
0'
b111 $
#2820
1!
1%
#2840
0!
0%
#2860
1!
1%
#2880
0!
0%
#2900
1!
1%
#2920
0!
0%
#2940
1!
1%
#2960
0!
0%
#2980
1!
1%
#3000
0!
0%
#3020
1!
1%
#3040
0!
0%
#3060
1!
1%
#3080
0!
0%
#3100
1!
1%
#3120
0!
0%
#3140
1!
1%
#3160
0!
0%
#3180
b1000101 "
b1000101 &
b11 (
b10110101 *
1!
1%
1#
1'
#3200
0!
0%
0#
0'
b1000 $
#3220
1!
1%
#3240
0!
0%
#3260
1!
1%
#3280
0!
0%
#3300
1!
1%
#3320
0!
0%
#3340
1!
1%
#3360
0!
0%
#3380
1!
1%
#3400
0!
0%
#3420
1!
1%
#3440
0!
0%
#3460
1!
1%
#3480
0!
0%
#3500
1!
1%
#3520
0!
0%
#3540
1!
1%
#3560
0!
0%
#3580
b1010000 "
b1010000 &
b11 (
b11001010 *
1!
1%
1#
1'
#3600
0!
0%
0#
0'
b1001 $
#3620
1!
1%
#3640
0!
0%
#3660
1!
1%
#3680
0!
0%
#3700
1!
1%
#3720
0!
0%
#3740
1!
1%
#3760
0!
0%
#3780
1!
1%
#3800
0!
0%
#3820
1!
1%
#3840
0!
0%
#3860
1!
1%
#3880
0!
0%
#3900
1!
1%
#3920
0!
0%
#3940
1!
1%
#3960
0!
0%
#3980
b1010101 "
b1010101 &
b11 (
b11100101 *
1!
1%
1#
1'
#4000
0!
0%
0#
0'
b1010 $
#4020
1!
1%
#4040
0!
0%
#4060
1!
1%
#4080
0!
0%
#4100
1!
1%
#4120
0!
0%
#4140
1!
1%
#4160
0!
0%
#4180
1!
1%
#4200
0!
0%
#4220
1!
1%
#4240
0!
0%
#4260
1!
1%
#4280
0!
0%
#4300
1!
1%
#4320
0!
0%
#4340
1!
1%
#4360
0!
0%
#4380
b1100000 "
b1100000 &
b11 (
b11111010 *
1!
1%
1#
1'
#4400
0!
0%
0#
0'
b1011 $
#4420
1!
1%
#4440
0!
0%
#4460
1!
1%
#4480
0!
0%
#4500
1!
1%
#4520
0!
0%
#4540
1!
1%
#4560
0!
0%
#4580
1!
1%
#4600
0!
0%
#4620
1!
1%
#4640
0!
0%
#4660
1!
1%
#4680
0!
0%
#4700
1!
1%
#4720
0!
0%
#4740
1!
1%
#4760
0!
0%
#4780
b1100101 "
b1100101 &
b11 (
b100010101 *
1!
1%
1#
1'
#4800
0!
0%
b1100 $
